MANIFEST.in
README.md
setup.py
valkka/multiprocess/__init__.py
valkka/multiprocess/base.py
valkka/multiprocess/sync.py
valkka_multiprocess.egg-info/PKG-INFO
valkka_multiprocess.egg-info/SOURCES.txt
valkka_multiprocess.egg-info/dependency_links.txt
valkka_multiprocess.egg-info/top_level.txt